<?xml version="1.0"?>
<zone number="62" name="The Orc Enclave" bottom="6200" top="6299" lifespan="20" reset_mode="2" mini_mud="false" rooms="68" mobiles="14" items="6" shops="0">
	<resets>
		<reset number="1" if_flag="false" type="M" arg1="6200" arg2="3" arg3="6219" />
		<reset number="2" if_flag="false" type="M" arg1="6200" arg2="3" arg3="6224" />
		<reset number="3" if_flag="false" type="M" arg1="6200" arg2="3" arg3="6218" />
		<reset number="4" if_flag="false" type="M" arg1="6201" arg2="2" arg3="6219" />
		<reset number="5" if_flag="false" type="M" arg1="6201" arg2="2" arg3="6224" />
		<reset number="6" if_flag="false" type="M" arg1="6202" arg2="3" arg3="6227" />
		<reset number="7" if_flag="false" type="M" arg1="6202" arg2="3" arg3="6224" />
		<reset number="8" if_flag="false" type="M" arg1="6202" arg2="3" arg3="6238" />
		<reset number="9" if_flag="false" type="M" arg1="6203" arg2="10" arg3="6234" />
		<reset number="10" if_flag="true" type="E" arg1="6204" arg2="1" arg3="16" />
		<reset number="11" if_flag="false" type="M" arg1="6203" arg2="10" arg3="6240" />
		<reset number="12" if_flag="true" type="E" arg1="6204" arg2="1" arg3="16" />
		<reset number="13" if_flag="false" type="M" arg1="6203" arg2="10" arg3="6236" />
		<reset number="14" if_flag="true" type="E" arg1="6204" arg2="1" arg3="16" />
		<reset number="15" if_flag="false" type="M" arg1="6203" arg2="10" arg3="6229" />
		<reset number="16" if_flag="true" type="E" arg1="6204" arg2="1" arg3="16" />
		<reset number="17" if_flag="false" type="M" arg1="6203" arg2="10" arg3="6212" />
		<reset number="18" if_flag="true" type="E" arg1="6204" arg2="1" arg3="16" />
		<reset number="19" if_flag="false" type="M" arg1="6203" arg2="10" arg3="6221" />
		<reset number="20" if_flag="true" type="E" arg1="6204" arg2="1" arg3="16" />
		<reset number="21" if_flag="false" type="M" arg1="6203" arg2="10" arg3="6223" />
		<reset number="22" if_flag="true" type="E" arg1="6204" arg2="1" arg3="16" />
		<reset number="23" if_flag="false" type="M" arg1="6203" arg2="10" arg3="6225" />
		<reset number="24" if_flag="true" type="E" arg1="6204" arg2="1" arg3="16" />
		<reset number="25" if_flag="false" type="M" arg1="6203" arg2="10" arg3="6214" />
		<reset number="26" if_flag="true" type="E" arg1="6204" arg2="1" arg3="16" />
		<reset number="27" if_flag="false" type="M" arg1="6203" arg2="10" arg3="6230" />
		<reset number="28" if_flag="true" type="E" arg1="6204" arg2="1" arg3="16" />
		<reset number="29" if_flag="false" type="M" arg1="6204" arg2="1" arg3="6252" />
		<reset number="30" if_flag="true" type="E" arg1="6204" arg2="1" arg3="16" />
		<reset number="31" if_flag="false" type="M" arg1="6205" arg2="3" arg3="6253" />
		<reset number="32" if_flag="false" type="M" arg1="6205" arg2="3" arg3="6250" />
		<reset number="33" if_flag="false" type="M" arg1="6205" arg2="3" arg3="6249" />
		<reset number="34" if_flag="false" type="M" arg1="6206" arg2="2" arg3="6246" />
		<reset number="35" if_flag="false" type="M" arg1="6206" arg2="2" arg3="6251" />
		<reset number="36" if_flag="false" type="M" arg1="6207" arg2="1" arg3="6253" />
		<reset number="37" if_flag="false" type="M" arg1="6208" arg2="2" arg3="6254" />
		<reset number="38" if_flag="false" type="M" arg1="6208" arg2="2" arg3="6254" />
		<reset number="39" if_flag="false" type="M" arg1="6209" arg2="3" arg3="6251" />
		<reset number="40" if_flag="true" type="E" arg1="6204" arg2="1" arg3="16" />
		<reset number="41" if_flag="false" type="M" arg1="6209" arg2="3" arg3="6250" />
		<reset number="42" if_flag="true" type="E" arg1="6204" arg2="1" arg3="16" />
		<reset number="43" if_flag="false" type="M" arg1="6209" arg2="3" arg3="6244" />
		<reset number="44" if_flag="true" type="E" arg1="6204" arg2="1" arg3="16" />
		<reset number="45" if_flag="false" type="M" arg1="6210" arg2="1" arg3="6259" />
		<reset number="46" if_flag="true" type="E" arg1="6205" arg2="1" arg3="16" />
		<reset number="47" if_flag="true" type="E" arg1="6203" arg2="1" arg3="17" />
		<reset number="48" if_flag="false" type="M" arg1="6211" arg2="1" arg3="6216" />
		<reset number="49" if_flag="true" type="G" arg1="6200" arg2="1" />
		<reset number="50" if_flag="false" type="M" arg1="6212" arg2="4" arg3="6267" />
		<reset number="51" if_flag="false" type="M" arg1="6212" arg2="4" arg3="6264" />
		<reset number="52" if_flag="false" type="M" arg1="6212" arg2="4" arg3="6261" />
		<reset number="53" if_flag="false" type="M" arg1="6213" arg2="1" arg3="6265" />
		<reset number="54" if_flag="true" type="E" arg1="6201" arg2="1" arg3="9" />
		<reset number="55" if_flag="true" type="E" arg1="6202" arg2="1" arg3="8" />
		<reset number="56" if_flag="false" type="D" arg1="6255" arg2="3" arg3="2" />
		<reset number="57" if_flag="false" type="D" arg1="6256" arg2="1" arg3="2" />
		<reset number="58" if_flag="false" type="D" arg1="6256" arg2="3" arg3="1" />
		<reset number="59" if_flag="false" type="D" arg1="6257" arg2="1" arg3="1" />
		<reset number="60" if_flag="false" type="D" arg1="6266" arg2="1" arg3="1" />
		<reset number="61" if_flag="false" type="D" arg1="6267" arg2="3" arg3="1" />
		<reset number="62" if_flag="false" type="D" arg1="6263" arg2="1" arg3="1" />
		<reset number="63" if_flag="false" type="D" arg1="6264" arg2="3" arg3="1" />
		<reset number="64" if_flag="false" type="D" arg1="6260" arg2="1" arg3="1" />
		<reset number="65" if_flag="false" type="D" arg1="6261" arg2="3" arg3="1" />
	</resets>
</zone>
