<?xml version="1.0"?>
<zone number="63" name="Arachnos" bottom="6300" top="6399" lifespan="34" reset_mode="2" mini_mud="false" rooms="52" mobiles="17" items="6" shops="0">
	<resets>
		<reset number="1" if_flag="false" type="M" arg1="6301" arg2="10" arg3="6301" />
		<reset number="2" if_flag="false" type="M" arg1="6301" arg2="10" arg3="6306" />
		<reset number="3" if_flag="false" type="M" arg1="6301" arg2="10" arg3="6306" />
		<reset number="4" if_flag="false" type="M" arg1="6301" arg2="10" arg3="6304" />
		<reset number="5" if_flag="false" type="M" arg1="6305" arg2="1" arg3="6303" />
		<reset number="6" if_flag="false" type="M" arg1="6310" arg2="1" arg3="6342" />
		<reset number="7" if_flag="false" type="M" arg1="6303" arg2="1" arg3="6313" />
		<reset number="8" if_flag="false" type="M" arg1="6308" arg2="5" arg3="6308" />
		<reset number="9" if_flag="false" type="M" arg1="6308" arg2="5" arg3="6308" />
		<reset number="10" if_flag="false" type="M" arg1="6308" arg2="5" arg3="6308" />
		<reset number="11" if_flag="false" type="M" arg1="6308" arg2="5" arg3="6308" />
		<reset number="12" if_flag="false" type="M" arg1="6308" arg2="5" arg3="6308" />
		<reset number="13" if_flag="false" type="M" arg1="6309" arg2="2" arg3="6327" />
		<reset number="14" if_flag="false" type="M" arg1="6307" arg2="5" arg3="6335" />
		<reset number="15" if_flag="false" type="M" arg1="6307" arg2="5" arg3="6333" />
		<reset number="16" if_flag="false" type="M" arg1="6304" arg2="1" arg3="6332" />
		<reset number="17" if_flag="true" type="G" arg1="6300" arg2="1" />
		<reset number="18" if_flag="false" type="M" arg1="6306" arg2="3" arg3="6321" />
		<reset number="19" if_flag="true" type="G" arg1="6305" arg2="10" />
		<reset number="20" if_flag="false" type="M" arg1="6306" arg2="3" arg3="6331" />
		<reset number="21" if_flag="true" type="G" arg1="6305" arg2="10" />
		<reset number="22" if_flag="false" type="M" arg1="6311" arg2="1" arg3="6373" />
		<reset number="23" if_flag="true" type="G" arg1="6302" arg2="2" />
		<reset number="24" if_flag="false" type="M" arg1="6315" arg2="1" arg3="6350" />
		<reset number="25" if_flag="true" type="G" arg1="6109" arg2="10" />
		<reset number="26" if_flag="true" type="G" arg1="6109" arg2="10" />
		<reset number="27" if_flag="false" type="M" arg1="6314" arg2="1" arg3="6399" />
		<reset number="28" if_flag="true" type="G" arg1="6301" arg2="5" />
		<reset number="29" if_flag="true" type="G" arg1="6302" arg2="2" />
		<reset number="30" if_flag="true" type="G" arg1="6303" arg2="2" />
		<reset number="31" if_flag="true" type="G" arg1="6304" arg2="2" />
		<reset number="32" if_flag="false" type="M" arg1="6312" arg2="1" arg3="6370" />
		<reset number="33" if_flag="true" type="G" arg1="6301" arg2="5" />
		<reset number="34" if_flag="true" type="G" arg1="6109" arg2="10" />
		<reset number="35" if_flag="false" type="M" arg1="6313" arg2="1" arg3="6367" />
		<reset number="36" if_flag="false" type="M" arg1="6306" arg2="3" arg3="6330" />
		<reset number="37" if_flag="false" type="M" arg1="6302" arg2="1" arg3="6360" />
		<reset number="38" if_flag="true" type="G" arg1="6304" arg2="2" />
		<reset number="39" if_flag="true" type="G" arg1="7203" arg2="1" />
		<reset number="40" if_flag="false" type="M" arg1="6316" arg2="1" arg3="6330" />
		<reset number="41" if_flag="false" type="M" arg1="6317" arg2="1" arg3="6340" />
		<reset number="42" if_flag="false" type="D" arg1="6392" arg2="0" arg3="2" />
		<reset number="43" if_flag="false" type="D" arg1="6399" arg2="2" arg3="2" />
	</resets>
</zone>
